streambird/__init__.py
streambird/_version.py
streambird/api.py
streambird/exceptions.py
streambird/api_resources/__init__.py
streambird/api_resources/magic_link.py
streambird/api_resources/oauth.py
streambird/api_resources/otp.py
streambird/api_resources/session.py
streambird/api_resources/totp.py
streambird/api_resources/user.py
streambird/api_resources/wallet.py
streambird-1.0.7.dist-info/LICENSE
streambird-1.0.7.dist-info/METADATA
streambird-1.0.7.dist-info/WHEEL
streambird-1.0.7.dist-info/top_level.txt
streambird-1.0.7.dist-info/RECORD
