Metadata-Version: 2.1
Name: streambird
Version: 1.0.7
Summary: The official Python client library for Streambird.io, the Passwordless Authentication Platform
Home-page: https://github.com/streambird/streambird-python
Author: Streambird
Author-email: support@streambird.io
License: UNKNOWN
Keywords: passwordless,streambird,authentication,otp,magiclinks,web3
Platform: UNKNOWN
Classifier: Development Status :: 5 - Production/Stable
Classifier: Natural Language :: English
Classifier: Programming Language :: Python
Classifier: Programming Language :: Python :: 3.6
Classifier: Programming Language :: Python :: 3.7
Classifier: Programming Language :: Python :: 3.8
Classifier: Programming Language :: Python :: 3.9
Classifier: Programming Language :: Python :: 3.10
Classifier: License :: OSI Approved :: MIT License
Classifier: Intended Audience :: Developers
Classifier: Topic :: Software Development :: Libraries
Requires-Python: >=3.6
License-File: LICENSE
Requires-Dist: requests (>=2.25.0)
Requires-Dist: urllib3 (>=1.26.0)
